{
  "version": "1.0.0",
  "restore": {
    "projectUniqueName": "/home/wangpc/WorkSpace/31Huiyi/MultiTenancyDemo/src/MultiTenancyDemo.csproj",
    "projectName": "MultiTenancyDemo",
    "projectPath": "/home/wangpc/WorkSpace/31Huiyi/MultiTenancyDemo/src/MultiTenancyDemo.csproj",
    "outputPath": "/home/wangpc/WorkSpace/31Huiyi/MultiTenancyDemo/src/obj/",
    "projectStyle": "PackageReference",
    "fallbackFolders": [
      "/usr/share/dotnet/sdk/NuGetFallbackFolder"
    ],
    "originalTargetFrameworks": [
      "netcoreapp2.1"
    ],
    "frameworks": {
      "netcoreapp2.1": {
        "projectReferences": {}
      }
    },
    "warningProperties": {
      "warnAsError": [
        "NU1605"
      ]
    }
  },
  "frameworks": {
    "netcoreapp2.1": {
      "dependencies": {
        "Microsoft.AspNetCore.App": {
          "suppressParent": "All",
          "target": "Package",
          "version": "[2.1.1, )",
          "autoReferenced": true
        },
        "Microsoft.NETCore.App": {
          "suppressParent": "All",
          "target": "Package",
          "version": "[2.1.0, )",
          "autoReferenced": true
        },
        "Newtonsoft.Json": {
          "target": "Package",
          "version": "[11.0.2, )"
        },
        "Pomelo.EntityFrameworkCore.MySql": {
          "target": "Package",
          "version": "[2.1.1, )"
        },
        "StackExchange.Redis": {
          "target": "Package",
          "version": "[2.0.0-alpha.200, )"
        }
      },
      "imports": [
        "net461"
      ],
      "assetTargetFallback": true,
      "warn": true
    }
  }
}